bot.py
logging_setup.py
master.py
project_repository.py
command_center/__init__.py
command_center/defaults.py
command_center/fsm.py
command_center/models.py
command_center/prompts.py
command_center/service.py
scripts/__init__.py
scripts/bump_version.sh
scripts/gen_preview.sh
scripts/git_pull_all.sh
scripts/git_push_all.sh
scripts/git_sync_all.sh
scripts/log_writer.py
scripts/master_healthcheck.py
scripts/publish.sh
scripts/requirements.txt
scripts/run_bot.sh
scripts/session_binder.py
scripts/start.sh
scripts/start_tmux_codex.sh
scripts/stop_all.sh
scripts/stop_bot.sh
scripts/test_deps_check.sh
scripts/wx_preview.sh
scripts/.venv/lib/python3.14/site-packages/pip/__init__.py
scripts/.venv/lib/python3.14/site-packages/pip/__main__.py
scripts/.venv/lib/python3.14/site-packages/pip/__pip-runner__.py
scripts/.venv/lib/python3.14/site-packages/pip/_internal/__init__.py
scripts/.venv/lib/python3.14/site-packages/pip/_internal/build_env.py
scripts/.venv/lib/python3.14/site-packages/pip/_internal/cache.py
scripts/.venv/lib/python3.14/site-packages/pip/_internal/configuration.py
scripts/.venv/lib/python3.14/site-packages/pip/_internal/exceptions.py
scripts/.venv/lib/python3.14/site-packages/pip/_internal/main.py
scripts/.venv/lib/python3.14/site-packages/pip/_internal/pyproject.py
scripts/.venv/lib/python3.14/site-packages/pip/_internal/self_outdated_check.py
scripts/.venv/lib/python3.14/site-packages/pip/_internal/wheel_builder.py
scripts/.venv/lib/python3.14/site-packages/pip/_internal/cli/__init__.py
scripts/.venv/lib/python3.14/site-packages/pip/_internal/cli/autocompletion.py
scripts/.venv/lib/python3.14/site-packages/pip/_internal/cli/base_command.py
scripts/.venv/lib/python3.14/site-packages/pip/_internal/cli/cmdoptions.py
scripts/.venv/lib/python3.14/site-packages/pip/_internal/cli/command_context.py
scripts/.venv/lib/python3.14/site-packages/pip/_internal/cli/index_command.py
scripts/.venv/lib/python3.14/site-packages/pip/_internal/cli/main.py
vibego-1.5.2.dist-info/licenses/LICENSE
vibego-1.5.2.dist-info/METADATA
vibego-1.5.2.dist-info/WHEEL
vibego-1.5.2.dist-info/entry_points.txt
vibego-1.5.2.dist-info/top_level.txt
vibego-1.5.2.dist-info/RECORD
