Metadata-Version: 2.4
Name: vibego
Version: 1.5.2
Summary: vibego CLI：用于初始化与管理 Telegram Master Bot 的工具
Author: Hypha
License-Expression: LicenseRef-Proprietary
Classifier: Programming Language :: Python :: 3
Classifier: Programming Language :: Python :: 3.9
Classifier: Programming Language :: Python :: 3.10
Classifier: Programming Language :: Python :: 3.11
Classifier: Operating System :: MacOS
Classifier: Intended Audience :: Developers
Classifier: Topic :: Software Development :: Build Tools
Classifier: Environment :: Console
Requires-Python: >=3.9
License-File: LICENSE
Requires-Dist: aiogram<4.0.0,>=3.0.0
Requires-Dist: aiohttp-socks>=0.10.0
Requires-Dist: aiosqlite>=0.19.0
Requires-Dist: markdown-it-py<4.0.0,>=3.0.0
Dynamic: license-file
